gitlabchangelog/VERSION
gitlabchangelog/__init__.py
gitlabchangelog/changelog.py
gitlabchangelog/version.py
GitLabChangelog-0.2.1.dist-info/LICENSE
GitLabChangelog-0.2.1.dist-info/METADATA
GitLabChangelog-0.2.1.dist-info/WHEEL
GitLabChangelog-0.2.1.dist-info/top_level.txt
GitLabChangelog-0.2.1.dist-info/RECORD
