Metadata-Version: 2.1
Name: GitLabChangelog
Version: 0.2.1
Summary: Produces GitLab changelog release notes for projects that follow SemVer
Home-page: https://github.com/invenia/gitlabchangelog
Author: Invenia Technical Computing
License: UNKNOWN
Platform: any
Classifier: Environment :: Console
Classifier: Intended Audience :: Developers
Classifier: License :: OSI Approved :: MIT License
Classifier: Operating System :: OS Independent
Classifier: Programming Language :: Python
Classifier: Programming Language :: Python :: 3.8
Classifier: Programming Language :: Python :: 3.9
License-File: LICENSE
Requires-Dist: Jinja2 (>=2.10.3)
Requires-Dist: python-dateutil (>=2.8.1)
Requires-Dist: python-gitlab (<3.0.0,>=1.8.0)
Requires-Dist: semver (>=2.9.0)
Provides-Extra: check
Requires-Dist: isort ; extra == 'check'
Requires-Dist: flake8 ; extra == 'check'
Requires-Dist: flake8-quotes ; extra == 'check'
Requires-Dist: pep8-naming ; extra == 'check'
Requires-Dist: mypy ; extra == 'check'
Requires-Dist: black ; extra == 'check'
Requires-Dist: types-python-dateutil ; extra == 'check'
Provides-Extra: dev
Requires-Dist: coverage[toml] ; extra == 'dev'
Requires-Dist: pytest ; extra == 'dev'
Requires-Dist: pytest-cov ; extra == 'dev'
Requires-Dist: sphinx ; extra == 'dev'
Requires-Dist: sphinx-rtd-theme ; extra == 'dev'
Requires-Dist: sphinx-autoapi ; extra == 'dev'
Requires-Dist: recommonmark ; extra == 'dev'
Requires-Dist: isort ; extra == 'dev'
Requires-Dist: flake8 ; extra == 'dev'
Requires-Dist: flake8-quotes ; extra == 'dev'
Requires-Dist: pep8-naming ; extra == 'dev'
Requires-Dist: mypy ; extra == 'dev'
Requires-Dist: black ; extra == 'dev'
Requires-Dist: types-python-dateutil ; extra == 'dev'
Provides-Extra: docs
Requires-Dist: sphinx ; extra == 'docs'
Requires-Dist: sphinx-rtd-theme ; extra == 'docs'
Requires-Dist: sphinx-autoapi ; extra == 'docs'
Requires-Dist: recommonmark ; extra == 'docs'
Provides-Extra: test
Requires-Dist: coverage[toml] ; extra == 'test'
Requires-Dist: pytest ; extra == 'test'
Requires-Dist: pytest-cov ; extra == 'test'
